ausnumtools/__init__.py
ausnumtools/ausnumtools.py
ausnumtools/setup.py
ausnumtools-1.2.0.dist-info/licenses/LICENSES/CC0-1.0.txt
ausnumtools-1.2.0.dist-info/licenses/LICENSES/GPL-3.0-only.txt
ausnumtools-1.2.0.dist-info/METADATA
ausnumtools-1.2.0.dist-info/WHEEL
ausnumtools-1.2.0.dist-info/top_level.txt
ausnumtools-1.2.0.dist-info/RECORD
