Metadata-Version: 2.4
Name: ausnumtools
Version: 1.2.0
Summary: A lightweight Python module that validates Australian phone numbers.
Author-email: Ben Bonacci <ben@benbonacci.com>
License-Expression: GPL-3.0-only
Project-URL: Repository, https://code.benbonacci.com/ben/ausnumtools
Project-URL: Documentation, https://code.benbonacci.com/ben/ausnumtools/wiki
Project-URL: Issues, https://lists.benbonacci.com/ausnumtools-bugs
Keywords: australia,telephone,number,validation
Classifier: Development Status :: 5 - Production/Stable
Classifier: Environment :: Console
Classifier: Intended Audience :: Developers
Classifier: Intended Audience :: Telecommunications Industry
Classifier: Programming Language :: Python :: 3
Classifier: Natural Language :: English
Classifier: Operating System :: OS Independent
Classifier: Topic :: Communications :: Telephony
Classifier: Topic :: Software Development :: Libraries :: Python Modules
Classifier: Topic :: Utilities
Requires-Python: >=3.0
License-File: LICENSES/CC0-1.0.txt
License-File: LICENSES/GPL-3.0-only.txt
Dynamic: license-file
